pipli/__init__.py
pipli/main.py
pipli-1.0.3.dist-info/METADATA
pipli-1.0.3.dist-info/WHEEL
pipli-1.0.3.dist-info/entry_points.txt
pipli-1.0.3.dist-info/top_level.txt
pipli-1.0.3.dist-info/RECORD
