Metadata-Version: 2.2
Name: pipli
Version: 1.0.3
Summary: A CLI tool that automatically installs missing Python dependencies and runs the given command.
Home-page: https://github.com/paulrahul/pipli
Author: Rahul Paul
Author-email: devnull90210@gmail.com
Project-URL: Bug Tracker, https://github.com/paulrahul/pipli/issues
Classifier: Programming Language :: Python :: 3
Classifier: License :: OSI Approved :: MIT License
Classifier: Operating System :: OS Independent
Requires-Python: >=3.6
Dynamic: author
Dynamic: author-email
Dynamic: classifier
Dynamic: description
Dynamic: description-content-type
Dynamic: home-page
Dynamic: project-url
Dynamic: requires-python
Dynamic: summary
